hevy_api_wrapper/__init__.py
hevy_api_wrapper/client.py
hevy_api_wrapper/endpoints/__init__.py
hevy_api_wrapper/endpoints/exercise_history.py
hevy_api_wrapper/endpoints/exercise_templates.py
hevy_api_wrapper/endpoints/routine_folders.py
hevy_api_wrapper/endpoints/routines.py
hevy_api_wrapper/endpoints/workouts.py
hevy_api_wrapper/errors.py
hevy_api_wrapper/models/__init__.py
hevy_api_wrapper/models/create_custom_exercise.py
hevy_api_wrapper/models/create_custom_exercise_request_body.py
hevy_api_wrapper/models/create_custom_exercise_response.py
hevy_api_wrapper/models/custom_exercise_type.py
hevy_api_wrapper/models/deleted_workout.py
hevy_api_wrapper/models/equipment_category.py
hevy_api_wrapper/models/event.py
hevy_api_wrapper/models/exercise_history_entry.py
hevy_api_wrapper/models/exercise_history_response.py
hevy_api_wrapper/models/exercise_model.py
hevy_api_wrapper/models/exercise_template.py
hevy_api_wrapper/models/muscle_group.py
hevy_api_wrapper/models/paginated_exercise_templates.py
hevy_api_wrapper/models/paginated_routine_folders.py
hevy_api_wrapper/models/paginated_routines.py
hevy_api_wrapper/models/paginated_workout_events.py
hevy_api_wrapper/models/paginated_workouts.py
hevy_api_wrapper/models/post_routine_folder.py
hevy_api_wrapper/models/post_routine_folder_request_body.py
hevy_api_wrapper/models/post_routines_request_body.py
hevy_api_wrapper/models/post_routines_request_body_routine.py
hevy_api_wrapper/models/post_routines_request_exercise.py
hevy_api_wrapper/models/post_routines_request_set.py
hevy_api_wrapper/models/post_workouts_request_body.py
hevy_api_wrapper/models/post_workouts_request_body_workout.py
hevy_api_wrapper/models/post_workouts_request_exercise.py
hevy_api_wrapper/models/post_workouts_request_set.py
hevy_api_wrapper/models/put_routines_request_body.py
hevy_api_wrapper/models/put_routines_request_body_routine.py
hevy_api_wrapper/models/put_routines_request_exercise.py
hevy_api_wrapper/models/put_routines_request_set.py
hevy_api_wrapper-1.0.0.dist-info/METADATA
hevy_api_wrapper-1.0.0.dist-info/WHEEL
hevy_api_wrapper-1.0.0.dist-info/licenses/LICENSE
hevy_api_wrapper-1.0.0.dist-info/RECORD
