Metadata-Version: 2.4
Name: hevy-api-wrapper
Version: 1.0.0
Summary: Python API wrapper for the Hevy API (sync + async, typed models, retries, pagination)
License: MIT
License-File: LICENSE
Keywords: hevy,fitness,api,client,httpx
Author: Dominic Kuncik
Author-email: itsdomhd@gmail.com
Requires-Python: >=3.10,<4.0
Classifier: License :: OSI Approved :: MIT License
Classifier: Programming Language :: Python :: 3
Classifier: Programming Language :: Python :: 3.10
Classifier: Programming Language :: Python :: 3.11
Classifier: Programming Language :: Python :: 3.12
Classifier: Programming Language :: Python :: 3.13
Classifier: Programming Language :: Python :: 3.14
Requires-Dist: httpx (>=0.27.0)
Requires-Dist: pydantic (>=2.5.0)
Requires-Dist: typing-extensions (>=4.8.0)
Project-URL: Homepage, https://github.com/dkuncik/hevy-api-wrapper
Project-URL: Repository, https://github.com/dkuncik/hevy-api-wrapper
